runningman/__init__.py
runningman/backend.py
runningman/job.py
runningman/provider.py
runningman/utils.py
runningman/version.py
runningman/test/__init__.py
runningman/test/test_basic.py
runningman/test/test_job.py
runningman/test/test_memory.py
runningman/test/test_modes.py
runningman/test/test_utils.py
runningman-2.2.0.dist-info/LICENSE
runningman-2.2.0.dist-info/METADATA
runningman-2.2.0.dist-info/WHEEL
runningman-2.2.0.dist-info/top_level.txt
runningman-2.2.0.dist-info/RECORD
